e2t/__init__.py
e2t/mktdata/BYMA_Messages_pb2.py
e2t/mktdata/E2T_MDG_BYMA.py
e2t/mktdata/E2T_MDG_IBKR.py
e2t/mktdata/IBKR_Messages_pb2.py
e2t/mktdata/__init__.py
e2t/oms/BYMA_Messages_pb2.py
e2t/oms/E2T_OMS_BYMA.py
e2t/oms/E2T_OMS_IBKR.py
e2t/oms/IBKR_Messages_pb2.py
e2t/oms/__init__.py
e2tapi-1.2.0.dist-info/METADATA
e2tapi-1.2.0.dist-info/WHEEL
e2tapi-1.2.0.dist-info/top_level.txt
e2tapi-1.2.0.dist-info/RECORD
