Metadata-Version: 2.1
Name: e2tapi
Version: 1.2.0
Summary: SDK for e2t API
Home-page: http://gitlab.event2trading.com/utilities/e2tapi.git
Author: Event2trading
Author-email: admin@event2trading.com
License: MIT
Classifier: Programming Language :: Python :: 3
Classifier: License :: OSI Approved :: MIT License
Classifier: Operating System :: OS Independent
Requires-Python: >=3.6
Requires-Dist: protobuf ==3.20.3
